fqlag/__init__.py
fqlag/base.py
fqlag/cxd.py
fqlag/cxdf.py
fqlag/misc.py
fqlag/multi.py
fqlag/pcxd.py
fqlag/psd.py
fqlag/psdf.py
fqlag-0.3.5.dist-info/METADATA
fqlag-0.3.5.dist-info/WHEEL
fqlag-0.3.5.dist-info/licenses/LICENSE.txt
fqlag-0.3.5.dist-info/RECORD
