Metadata-Version: 2.4
Name: fqlag
Version: 0.3.5
Summary: Calculating Periodogram and Time delays in the frequency domain from unevenly-sample time series
Project-URL: Homepage, https://github.com/zoghbi-a/fqlag
Project-URL: Download, https://github.com/zoghbi-a/fqlag/archive/v0.3.1.tar.gz
Author-email: Abdu Zoghbi <astrozoghbi@gmail.com>
License: MIT License
License-File: LICENSE.txt
Keywords: Astronomy,Delays,Time-Series
Requires-Python: >=3.8
Requires-Dist: scipy
Provides-Extra: test
Requires-Dist: numdifftools; extra == 'test'
